Metadata-Version: 1.0
Name: watch-scraper
Version: 0.0.1
Summary: Aicore project that allows the user to scrape mens watch data from the gold smiths website
Home-page: UNKNOWN
Author: Tafadzwa Zama
Author-email: UNKNOWN
License: MIT
Platform: UNKNOWN
